drb_impl_java/__init__.py
drb_impl_java/_version.py
drb_impl_java/drb_impl_java_call.py
drb_impl_java/drb_impl_java_factory.py
drb_impl_java/drb_impl_java_node.py
drb_impl_java/drb_impl_java_stream.py
drb_impl_java-1.0.1.data/data/requirements.txt
drb_impl_java_jars/__init__.py
drb_impl_java_jars/antlr-2.7.5.jar
drb_impl_java_jars/arq-2.1.jar
drb_impl_java_jars/arq-extra-2.1.jar
drb_impl_java_jars/bsh-2.0b4.jar
drb_impl_java_jars/commons-codec-1.4.jar
drb_impl_java_jars/commons-logging-api-1.1.jar
drb_impl_java_jars/concurrent-jena-1.3.2.jar
drb_impl_java_jars/cortex-core-1.0.3.jar
drb_impl_java_jars/drb-2-SNAPSHOT.jar
drb_impl_java_jars/drbx-cortex-1.0.8.jar
drb_impl_java_jars/drbx-impl-interface-python-1-SNAPSHOT.jar
drb_impl_java_jars/ehcache-2.10.1.jar
drb_impl_java_jars/ehcache-core-2.5.0.jar
drb_impl_java_jars/icu4j-4.8.2.jar
drb_impl_java_jars/iri-0.5.jar
drb_impl_java_jars/jcommander-1.27.jar
drb_impl_java_jars/jena-2.5.4.jar
drb_impl_java_jars/jenatest-2.5.4.jar
drb_impl_java_jars/json-jena-1.0.jar
drb_impl_java_jars/log4j-1.2.8.jar
drb_impl_java_jars/log4j-api-2.8.2.jar
drb_impl_java_jars/log4j-core-2.8.2.jar
drb_impl_java_jars/lucene-core-2.0.0.jar
drb_impl_java_jars/org.osgi.core-4.0.0.jar
drb_impl_java_jars/org.restlet-2.0.5.jar
drb_impl_java_jars/slf4j-api-1.7.7.jar
drb_impl_java_jars/stax-api-1.0.jar
drb_impl_java_jars/streams-1.0.19.jar
drb_impl_java_jars/testng-6.8.13.jar
drb_impl_java_jars/wstx-asl-3.0.0.jar
drb_impl_java_jars/xercesImpl-2.7.1.jar
drb_impl_java_jars/xmlParserAPIs-2.0.2.jar
drb_impl_java-1.0.1.dist-info/METADATA
drb_impl_java-1.0.1.dist-info/WHEEL
drb_impl_java-1.0.1.dist-info/top_level.txt
drb_impl_java-1.0.1.dist-info/RECORD
