Metadata-Version: 2.1
Name: drb-impl-java
Version: 1.0.1
Summary: DRB Java implementation
Home-page: https://gitlab.com/drb-python/impl/java
Author: GAEL Systems
Author-email: drb-python@gael.fr
License: UNKNOWN
Platform: UNKNOWN
Classifier: Programming Language :: Python :: 3.8
Classifier: License :: OSI Approved :: Apache Software License
Classifier: Operating System :: OS Independent
Requires-Python: >=3.8
Requires-Dist: jip
Requires-Dist: cython
Requires-Dist: drb (<1.1.0,>=1.0.1)
Requires-Dist: versioneer (>=0.20)
Requires-Dist: jnius
Requires-Dist: pyjnius (>=1.4.1)
